<annotation>
  <folder>input</folder>
  <filename>img2019-05-28-16-24-44-154008.jpg</filename>
  <path>D:\OpenLabeling\main\input\img2019-05-28-16-24-44-154008.jpg</path>
  <source>
    <database>Unknown</database>
  </source>
  <size>
    <width>416</width>
    <height>416</height>
    <depth>3</depth>
  </size>
  <segmented>0</segmented>
  <object>
    <name>black-info-7</name>
    <pose>Unspecified</pose>
    <truncated>0</truncated>
    <difficult>0</difficult>
    <bndbox>
      <xmin>104</xmin>
      <ymin>30</ymin>
      <xmax>159</xmax>
      <ymax>325</ymax>
    </bndbox>
  </object>
  <object>
    <name>black-info-6</name>
    <pose>Unspecified</pose>
    <truncated>0</truncated>
    <difficult>0</difficult>
    <bndbox>
      <xmin>277</xmin>
      <ymin>170</ymin>
      <xmax>288</xmax>
      <ymax>219</ymax>
    </bndbox>
  </object>
</annotation>
