<annotation>
  <folder>input</folder>
  <filename>img2019-05-28-16-06-39-104903.jpg</filename>
  <path>D:\OpenLabeling\main\input\img2019-05-28-16-06-39-104903.jpg</path>
  <source>
    <database>Unknown</database>
  </source>
  <size>
    <width>416</width>
    <height>416</height>
    <depth>3</depth>
  </size>
  <segmented>0</segmented>
  <object>
    <name>white-info-4</name>
    <pose>Unspecified</pose>
    <truncated>0</truncated>
    <difficult>0</difficult>
    <bndbox>
      <xmin>24</xmin>
      <ymin>98</ymin>
      <xmax>62</xmax>
      <ymax>264</ymax>
    </bndbox>
  </object>
  <object>
    <name>white-info-3</name>
    <pose>Unspecified</pose>
    <truncated>0</truncated>
    <difficult>0</difficult>
    <bndbox>
      <xmin>115</xmin>
      <ymin>153</ymin>
      <xmax>123</xmax>
      <ymax>216</ymax>
    </bndbox>
  </object>
</annotation>
